AUTHORS.rst
CONTRIBUTING.rst
HISTORY.rst
LICENSE
MANIFEST.in
README.rst
setup.cfg
setup.py
mozilla_django_oidc_hta/__init__.py
mozilla_django_oidc_hta/auth.py
mozilla_django_oidc_hta/middleware.py
mozilla_django_oidc_hta/urls.py
mozilla_django_oidc_hta/utils.py
mozilla_django_oidc_hta/views.py
mozilla_django_oidc_hta.egg-info/PKG-INFO
mozilla_django_oidc_hta.egg-info/SOURCES.txt
mozilla_django_oidc_hta.egg-info/dependency_links.txt
mozilla_django_oidc_hta.egg-info/not-zip-safe
mozilla_django_oidc_hta.egg-info/requires.txt
mozilla_django_oidc_hta.egg-info/top_level.txt