Metadata-Version: 1.1
Name: mozilla-django-oidc-hta
Version: 1.1.2
Summary: A lightweight authentication and access management library for integration with OpenID Connect enabled authentication services.
Home-page: https://github.com/mozilla/mozilla-django-oidc
Author: Tasos Katsoulas, John Giannelos
Author-email: akatsoulas@mozilla.com, jgiannelos@mozilla.com
License: MPL 2.0
Keywords: mozilla-django-oidc-hta
Platform: UNKNOWN
Classifier: Development Status :: 5 - Production/Stable
Classifier: Framework :: Django
Classifier: Framework :: Django :: 1.11
Classifier: Framework :: Django :: 2.0
Classifier: License :: OSI Approved :: Mozilla Public License 2.0 (MPL 2.0)
Classifier: Intended Audience :: Developers
Classifier: Operating System :: MacOS
Classifier: Operating System :: POSIX :: Linux
Classifier: Natural Language :: English
Classifier: Programming Language :: Python :: 2
Classifier: Programming Language :: Python :: 2.7
Classifier: Programming Language :: Python :: 3
Classifier: Programming Language :: Python :: 3.4
Classifier: Programming Language :: Python :: 3.5
Classifier: Programming Language :: Python :: 3.6
